{"title":"MarketsMojo – Stocks in Action","url":"https://www.marketsmojo.com/news/stocks-in-action","favicon":"https://i.marketsmojo.com/favicon-32x32.png","elements":[{"contents":"Stocks in Action","retrieved":1765032132263},{"contents":"Stock Recommendation","retrieved":1765032132264},{"contents":"Result Analysis","retrieved":1765032132265},{"contents":"Across The Web","retrieved":1765032132266},{"contents":"Stock Market News","retrieved":1765032132267},{"contents":"Mojo Premium","retrieved":1765032132268},{"contents":"<div class=\"card-title\"> Why is Bluestone Jewel falling/rising?</div>","retrieved":1765032132269},{"contents":"<p>As of 05-Dec, Bluestone Jewellery &amp; Lifestyle Ltd’s stock price has fallen sharply, reflecting a combination of weak financial performance, deteriorating fundamentals, and increased selling pressure from promoters, all contributing to the sustained downward trend in the share price. </p>","retrieved":1765032132270},{"title":"Why is Borana Weaves falling/rising?","contents":"<h2 class=\"card-title\"> Why is Borana Weaves falling/rising?</h2>","retrieved":1765032132334},{"title":"Why is Malpani Pipes falling/rising?","contents":"<h2 class=\"card-title\"> Why is Malpani Pipes falling/rising?</h2>","retrieved":1765032132335},{"title":"Why is Sat Kartar falling/rising?","contents":"<h2 class=\"card-title\"> Why is Sat Kartar falling/rising?</h2>","retrieved":1765032132335},{"title":"Why is Baazar Style falling/rising?","contents":"<h2 class=\"card-title\"> Why is Baazar Style falling/rising?</h2>","retrieved":1765032132336},{"title":"Why is Agarwal Toughene falling/rising?","contents":"<h2 class=\"card-title\"> Why is Agarwal Toughene falling/rising?</h2>","retrieved":1765032132336},{"title":"Why is Blackbuck falling/rising?","contents":"<h2 class=\"card-title\"> Why is Blackbuck falling/rising?</h2>","retrieved":1765032132337},{"title":"Why is Sathlokhar Sys. falling/rising?","contents":"<h2 class=\"card-title\"> Why is Sathlokhar Sys. falling/rising?</h2>","retrieved":1765032132337},{"title":"Why is Esprit Stones falling/rising?","contents":"<h2 class=\"card-title\"> Why is Esprit Stones falling/rising?</h2>","retrieved":1765032132338},{"title":"Why is Vraj Iron falling/rising?","contents":"<h2 class=\"card-title\"> Why is Vraj Iron falling/rising?</h2>","retrieved":1765032132339},{"title":"Why is Sahaj Solar falling/rising?","contents":"<h2 class=\"card-title\"> Why is Sahaj Solar falling/rising?</h2>","retrieved":1765032132340},{"title":"Why is Petro Carbon falling/rising?","contents":"<h2 class=\"card-title\"> Why is Petro Carbon falling/rising?</h2>","retrieved":1765032132341},{"title":"Why is Platinum Industr falling/rising?","contents":"<h2 class=\"card-title\"> Why is Platinum Industr falling/rising?</h2>","retrieved":1765032132342},{"title":"Why is Deem Roll-Tech falling/rising?","contents":"<h2 class=\"card-title\"> Why is Deem Roll-Tech falling/rising?</h2>","retrieved":1765032132343},{"title":"Why is Akanksha Power falling/rising?","contents":"<h2 class=\"card-title\"> Why is Akanksha Power falling/rising?</h2>","retrieved":1765032132344},{"title":"Why is Wise Travel falling/rising?","contents":"<h2 class=\"card-title\"> Why is Wise Travel falling/rising?</h2>","retrieved":1765032132345},{"title":"Why is Sar Televenture falling/rising?","contents":"<h2 class=\"card-title\"> Why is Sar Televenture falling/rising?</h2>","retrieved":1765032132346},{"title":"Why is Kody Technolab falling/rising?","contents":"<h2 class=\"card-title\"> Why is Kody Technolab falling/rising?</h2>","retrieved":1765032132347},{"title":"Why is Sharp Chucks and falling/rising?","contents":"<h2 class=\"card-title\"> Why is Sharp Chucks and falling/rising?</h2>","retrieved":1765032132348},{"title":"Why is Oriana Power Ltd falling/rising?","contents":"<h2 class=\"card-title\"> Why is Oriana Power Ltd falling/rising?</h2>","retrieved":1765032132350},{"contents":"<div class=\"card-title\"> Are Jagatjit Inds. latest results good or bad?</div>","retrieved":1765032132276},{"contents":"<div class=\"card-title\"> Phoenix Intl. Sees Revision in Market Evaluation Amid Mixed Financial Signals</div>","retrieved":1765032132276},{"contents":"<div class=\"card-title\"> Dhanalaxmi Roto Sees Revision in Market Evaluation Amid Mixed Financial Signals</div>","retrieved":1765032132278}]}