{"title":"MarketsMojo – Mojo Premium","url":"https://www.marketsmojo.com/news/mojo-premium","favicon":"https://i.marketsmojo.com/favicon-32x32.png","elements":[{"contents":"Sensex and Nifty Advance as Banking Sector Leads Gains Amid Mixed Market Breadth","retrieved":1765039660175},{"contents":"Stock Market News","retrieved":1765039660175},{"contents":"Read Full Story","retrieved":1765039660175},{"contents":"Across The Web","retrieved":1765039660175},{"contents":"Across The Web","retrieved":1765039660178},{"contents":"Sector Performance Snapshot: Banking, Finance, and IT Lead Gains Amid Mixed Market Sentiment","retrieved":1765039660178},{"contents":"Stock Market News","retrieved":1765039660178},{"contents":"Small-Cap Segment Faces Pressure Amid Mixed Market Signals","retrieved":1765039660178},{"contents":"Stock Market News","retrieved":1765039660178},{"contents":"See All <span class=\"material-symbols-outlined\">\n                            chevron_right\n                          </span>","retrieved":1765039660179},{"contents":"Large-Cap Segment Sees Mixed Trends as HCL Technologies and Axis Bank Lead Momentum","retrieved":1765039660180},{"contents":"Read Full Story","retrieved":1765039660181},{"contents":"Stock Market News","retrieved":1765039660182},{"contents":"Why is Interglobe Aviat falling/rising?","retrieved":1765039660183},{"contents":"Stocks in Action","retrieved":1765039660184},{"contents":"HCL Technologies Sees Shift in Market Assessment Amid Mixed Financial and Technical Signals","retrieved":1765039660185},{"contents":"Stock Recommendation","retrieved":1765039660186},{"contents":"See All <span class=\"material-symbols-outlined\">\n                            chevron_right\n                          </span>","retrieved":1765039660187},{"contents":"Mid-Cap Segment Sees Mixed Performance with M &amp; M Financial Services Leading Gains","retrieved":1765039660188},{"contents":"Read Full Story","retrieved":1765039660190},{"contents":"Stock Market News","retrieved":1765039660191},{"contents":"Why is Bluestone Jewel falling/rising?","retrieved":1765039660192},{"contents":"Stocks in Action","retrieved":1765039660193},{"contents":"Swiggy’s Market Assessment Reflects Challenges Amidst E-Retail Sector Dynamics","retrieved":1765039660194},{"contents":"Stock Recommendation","retrieved":1765039660195},{"contents":"See All <span class=\"material-symbols-outlined\">\n                            chevron_right\n                          </span>","retrieved":1765039660196},{"contents":"Small-Cap Segment Faces Pressure Amid Mixed Market Signals","retrieved":1765039660197},{"contents":"Read Full Story","retrieved":1765039660198},{"contents":"Stock Market News","retrieved":1765039660199},{"contents":"Vaghani Techno Sees Revision in Market Evaluation Amid Mixed Financial Signals","retrieved":1765039660200},{"contents":"Stock Recommendation","retrieved":1765039660201},{"contents":"Why is Baazar Style falling/rising?","retrieved":1765039660202},{"contents":"Stocks in Action","retrieved":1765039660203},{"contents":"<div class=\"card-title\"> Vodafone Idea Ltd: High-Value Trading and Institutional Interest Highlight Market Activity</div>","retrieved":1765039660204},{"contents":"<div class=\"card-title\"> Waaree Energies: Analytical Review Highlights Shift in Market Assessment</div>","retrieved":1765039660205},{"contents":"<div class=\"card-title\"> Suzlon Energy Sees Exceptional Trading Volume Amid Market Activity</div>","retrieved":1765039660207},{"contents":"<div class=\"card-title\"> Magellanic Cloud Stock Falls to 52-Week Low of Rs.27.41</div>","retrieved":1765039660207},{"contents":"<div class=\"card-title\"> Hindustan Construction Company Sees Exceptional Trading Volume Amid Market Activity</div>","retrieved":1765039660208},{"contents":"<div class=\"card-title\"> Dixon Technologies Sees Heavy Put Option Activity Amid Bearish Market Sentiment</div>","retrieved":1765039660209},{"contents":"<div class=\"card-title\"> Ola Electric Mobility Faces Intense Selling Pressure Amid Consecutive Losses</div>","retrieved":1765039660210},{"contents":"Stocks in Action","retrieved":1765039660211},{"contents":"Stock Recommendation","retrieved":1765039660213},{"contents":"Result Analysis","retrieved":1765039660214},{"contents":"Across The Web","retrieved":1765039660215},{"contents":"Stock Market News","retrieved":1765039660216},{"contents":"Mojo Premium","retrieved":1765039660217},{"title":"Are Jagatjit Inds. latest results good or bad?","contents":"<h2 class=\"card-title\">Are Jagatjit Inds. latest results good or bad?</h2>","retrieved":1765039660280},{"contents":"<p>Jagatjit Industries' latest Q2 FY26 results are poor, showing a net loss of ₹27.91 crores and a 52.90% drop in net sales year-on-year, alongside deteriorating margins and high leverage, indicating significant operational challenges and a need for strategic reassessment. </p>","retrieved":1765039660218},{"title":"Rajnish Retail’s Evaluation Revised Amid Mixed Financial and Market Signals","contents":"<h2 class=\"card-title\"> Rajnish Retail’s Evaluation Revised Amid Mixed Financial and Market Signals</h2>","retrieved":1765039660281},{"contents":"<img loading=\"lazy\" style=\"width:130px;height:85px\" alt=\"Rajnish Retail’s Evaluation Revised Amid Mixed Financial and Market Signals\" src=\"https://i.marketsmojo.com/newsimg/2025/12/RajnishRetail_mojoScore_3749801.png\" lazy-load-src=\"https://i.marketsmojo.com/newsimg/2025/12/RajnishRetail_mojoScore_3749801.png\" class=\"img-fluid articlepic\">","retrieved":1765039660219},{"title":"SPA CAPT SER Sees Revision in Market Evaluation Amidst Mixed Financial Signals","contents":"<h2 class=\"card-title\"> SPA CAPT SER Sees Revision in Market Evaluation Amidst Mixed Financial Signals</h2>","retrieved":1765039660282},{"contents":"<img loading=\"lazy\" style=\"width:130px;height:85px\" alt=\"SPA CAPT SER Sees Revision in Market Evaluation Amidst Mixed Financial Signals\" src=\"https://i.marketsmojo.com/newsimg/2025/12/SPACAPTSER_mojoScore_3749800.png\" lazy-load-src=\"https://i.marketsmojo.com/newsimg/2025/12/SPACAPTSER_mojoScore_3749800.png\" class=\"img-fluid articlepic\">","retrieved":1765039660220},{"title":"Trustedgecapital’s Evaluation Revised Amid Mixed Financial and Market Signals","contents":"<h2 class=\"card-title\"> Trustedgecapital’s Evaluation Revised Amid Mixed Financial and Market Signals</h2>","retrieved":1765039660282},{"contents":"<img loading=\"lazy\" style=\"width:130px;height:85px\" alt=\"Trustedgecapital’s Evaluation Revised Amid Mixed Financial and Market Signals\" src=\"https://i.marketsmojo.com/newsimg/2025/12/Trustedgecapita_mojoScore_3749803.png\" lazy-load-src=\"https://i.marketsmojo.com/newsimg/2025/12/Trustedgecapita_mojoScore_3749803.png\" class=\"img-fluid articlepic\">","retrieved":1765039660222},{"title":"Supreme Facility’s Evaluation Revised Amid Mixed Performance Indicators","contents":"<h2 class=\"card-title\"> Supreme Facility’s Evaluation Revised Amid Mixed Performance Indicators</h2>","retrieved":1765039660284},{"contents":"<img loading=\"lazy\" style=\"width:130px;height:85px\" alt=\"Supreme Facility’s Evaluation Revised Amid Mixed Performance Indicators\" src=\"https://i.marketsmojo.com/newsimg/2025/12/SupremeFacility_mojoScore_3749802.png\" lazy-load-src=\"https://i.marketsmojo.com/newsimg/2025/12/SupremeFacility_mojoScore_3749802.png\" class=\"img-fluid articlepic\">","retrieved":1765039660223},{"title":"Astal Lab’s Market Evaluation Revised Amidst Microcap Challenges","contents":"<h2 class=\"card-title\"> Astal Lab’s Market Evaluation Revised Amidst Microcap Challenges</h2>","retrieved":1765039660286},{"contents":"<img loading=\"lazy\" style=\"width:130px;height:85px\" alt=\"Astal Lab’s Market Evaluation Revised Amidst Microcap Challenges\" src=\"https://i.marketsmojo.com/newsimg/2025/12/AstalLab_mojoScore_3749798.png\" lazy-load-src=\"https://i.marketsmojo.com/newsimg/2025/12/AstalLab_mojoScore_3749798.png\" class=\"img-fluid articlepic\">","retrieved":1765039660224},{"title":"Yash Innoventure Sees Revision in Market Assessment Amid Challenging Fundamentals","contents":"<h2 class=\"card-title\"> Yash Innoventure Sees Revision in Market Assessment Amid Challenging Fundamentals</h2>","retrieved":1765039660287},{"contents":"<img loading=\"lazy\" style=\"width:130px;height:85px\" alt=\"Yash Innoventure Sees Revision in Market Assessment Amid Challenging Fundamentals\" src=\"https://i.marketsmojo.com/newsimg/2025/12/YashInnoventure_mojoScore_3749799.png\" lazy-load-src=\"https://i.marketsmojo.com/newsimg/2025/12/YashInnoventure_mojoScore_3749799.png\" class=\"img-fluid articlepic\">","retrieved":1765039660225},{"title":"Sharda Ispat Sees Revision in Market Evaluation Amidst Challenging Financial Trends","contents":"<h2 class=\"card-title\"> Sharda Ispat Sees Revision in Market Evaluation Amidst Challenging Financial Trends</h2>","retrieved":1765039660287},{"contents":"<img loading=\"lazy\" style=\"width:130px;height:85px\" alt=\"Sharda Ispat Sees Revision in Market Evaluation Amidst Challenging Financial Trends\" src=\"https://i.marketsmojo.com/newsimg/2025/12/ShardaIspat_mojoScore_3749796.png\" lazy-load-src=\"https://i.marketsmojo.com/newsimg/2025/12/ShardaIspat_mojoScore_3749796.png\" class=\"img-fluid articlepic\">","retrieved":1765039660226},{"title":"Accel Stock Evaluation Revised Amidst Challenging Market Conditions","contents":"<h2 class=\"card-title\"> Accel Stock Evaluation Revised Amidst Challenging Market Conditions</h2>","retrieved":1765039660289},{"contents":"<img loading=\"lazy\" style=\"width:130px;height:85px\" alt=\"Accel Stock Evaluation Revised Amidst Challenging Market Conditions\" src=\"https://i.marketsmojo.com/newsimg/2025/12/Accel_mojoScore_3749793.png\" lazy-load-src=\"https://i.marketsmojo.com/newsimg/2025/12/Accel_mojoScore_3749793.png\" class=\"img-fluid articlepic\">","retrieved":1765039660227},{"title":"Barak Valley’s Evaluation Revised Amid Challenging Fundamentals and Market Performance","contents":"<h2 class=\"card-title\"> Barak Valley’s Evaluation Revised Amid Challenging Fundamentals and Market Performance</h2>","retrieved":1765039660292},{"contents":"<img loading=\"lazy\" style=\"width:130px;height:85px\" alt=\"Barak Valley’s Evaluation Revised Amid Challenging Fundamentals and Market Performance\" src=\"https://i.marketsmojo.com/newsimg/2025/12/BarakValley_mojoScore_3749797.png\" lazy-load-src=\"https://i.marketsmojo.com/newsimg/2025/12/BarakValley_mojoScore_3749797.png\" class=\"img-fluid articlepic\">","retrieved":1765039660228},{"title":"Transcorp Intl. Evaluation Revised Amidst Weak Financial Trends and Market Underperformance","contents":"<h2 class=\"card-title\"> Transcorp Intl. Evaluation Revised Amidst Weak Financial Trends and Market Underperformance</h2>","retrieved":1765039660292},{"contents":"<img loading=\"lazy\" style=\"width:130px;height:85px\" alt=\"Transcorp Intl. Evaluation Revised Amidst Weak Financial Trends and Market Underperformance\" src=\"https://i.marketsmojo.com/newsimg/2025/12/TranscorpIntl_mojoScore_3749792.png\" lazy-load-src=\"https://i.marketsmojo.com/newsimg/2025/12/TranscorpIntl_mojoScore_3749792.png\" class=\"img-fluid articlepic\">","retrieved":1765039660229},{"title":"Auri Grow India Sees Revision in Market Evaluation Amid Mixed Financial Signals","contents":"<h2 class=\"card-title\"> Auri Grow India Sees Revision in Market Evaluation Amid Mixed Financial Signals</h2>","retrieved":1765039660293},{"contents":"<img loading=\"lazy\" style=\"width:130px;height:85px\" alt=\"Auri Grow India Sees Revision in Market Evaluation Amid Mixed Financial Signals\" src=\"https://i.marketsmojo.com/newsimg/2025/12/AuriGrowIndia_mojoScore_3749795.png\" lazy-load-src=\"https://i.marketsmojo.com/newsimg/2025/12/AuriGrowIndia_mojoScore_3749795.png\" class=\"img-fluid articlepic\">","retrieved":1765039660229},{"title":"Sancode Tech. Sees Revision in Market Assessment Amid Mixed Fundamentals","contents":"<h2 class=\"card-title\"> Sancode Tech. Sees Revision in Market Assessment Amid Mixed Fundamentals</h2>","retrieved":1765039660294},{"contents":"<img loading=\"lazy\" style=\"width:130px;height:85px\" alt=\"Sancode Tech. Sees Revision in Market Assessment Amid Mixed Fundamentals\" src=\"https://i.marketsmojo.com/newsimg/2025/12/SancodeTech_mojoScore_3749791.png\" lazy-load-src=\"https://i.marketsmojo.com/newsimg/2025/12/SancodeTech_mojoScore_3749791.png\" class=\"img-fluid articlepic\">","retrieved":1765039660230},{"title":"Goyal Aluminiums Sees Revision in Market Evaluation Amidst Challenging Financial Trends","contents":"<h2 class=\"card-title\"> Goyal Aluminiums Sees Revision in Market Evaluation Amidst Challenging Financial Trends</h2>","retrieved":1765039660294},{"contents":"<img loading=\"lazy\" style=\"width:130px;height:85px\" alt=\"Goyal Aluminiums Sees Revision in Market Evaluation Amidst Challenging Financial Trends\" src=\"https://i.marketsmojo.com/newsimg/2025/12/GoyalAluminiums_mojoScore_3749794.png\" lazy-load-src=\"https://i.marketsmojo.com/newsimg/2025/12/GoyalAluminiums_mojoScore_3749794.png\" class=\"img-fluid articlepic\">","retrieved":1765039660231},{"title":"Ashnoor Textile Sees Revision in Market Assessment Amid Challenging Financial Trends","contents":"<h2 class=\"card-title\"> Ashnoor Textile Sees Revision in Market Assessment Amid Challenging Financial Trends</h2>","retrieved":1765039660295},{"contents":"<img loading=\"lazy\" style=\"width:130px;height:85px\" alt=\"Ashnoor Textile Sees Revision in Market Assessment Amid Challenging Financial Trends\" src=\"https://i.marketsmojo.com/newsimg/2025/12/AshnoorTextile_mojoScore_3749790.png\" lazy-load-src=\"https://i.marketsmojo.com/newsimg/2025/12/AshnoorTextile_mojoScore_3749790.png\" class=\"img-fluid articlepic\">","retrieved":1765039660232},{"title":"Jumbo Bag Sees Revision in Market Assessment Amid Mixed Financial Signals","contents":"<h2 class=\"card-title\"> Jumbo Bag Sees Revision in Market Assessment Amid Mixed Financial Signals</h2>","retrieved":1765039660296},{"contents":"<img loading=\"lazy\" style=\"width:130px;height:85px\" alt=\"Jumbo Bag Sees Revision in Market Assessment Amid Mixed Financial Signals\" src=\"https://i.marketsmojo.com/newsimg/2025/12/JumboBag_mojoScore_3749785.png\" lazy-load-src=\"https://i.marketsmojo.com/newsimg/2025/12/JumboBag_mojoScore_3749785.png\" class=\"img-fluid articlepic\">","retrieved":1765039660235}]}